{
    "dirs": [
        ["src"],
        ["include"],
        ["tests"],
        [".vscode"]
    ],
    "files_root": "c++",
    "files": [
        {
            "name": "^main\\.cpp$",
            "src_path": ["src"],
            "dst_path": ["src"]
        },
        {
            "name": "^test.*\\.cpp$",
            "src_path": ["tests"],
            "dst_path": ["tests"]
        },
        {
            "name": "^launch\\.json$",
            "src_path": ["configs"],
            "dst_path": [".vscode"]
        },
        {
            "src_name": "Windows_CMakePresets.json",
            "dst_name": "CMakePresets.json",
            "src_path": ["configs"],
            "dst_path": []
        },
        {
            "name": "^CMakeLists\\.txt$",
            "src_path": ["configs"],
            "dst_path": []
        },
        {
            "name": "^.*$",
            "src_path": ["github"],
            "dst_path": []
        }
    ]
}